{
  "$schema": "https://schemas.wp.org/trunk/block.json",
  "apiVersion": 2,
  "name": "cagov-design-system/page-navigation",
  "version": "2.1.0",
  "title": "Page Navigation",
  "category": "cagov-design-system",
  "icon": "format-aside",
  "description": "Page navigation lists and links to the level 2 headings of a webpage.",
  "supports": {
    "html": true
  },
  "attributes": {
    "title": {
      "type": "string"
    }
  },
  "textdomain": "cagov-design-system",
  "editorScript": "cagov-design-system-gutenberg",
  "editorStyle": "cagov-design-system-gutenberg",
  "style": "cagov-design-system-gutenberg-style"
}